specex/__init__.py
specex/_version.py
specex/cube.py
specex/cubex.py
specex/exceptions.py
specex/lines.py
specex/plot.py
specex/rrspecex.py
specex/sources.py
specex/stack.py
specex/utils.py
specex/zeropoints.py
specex-0.7.13.dist-info/licenses/LICENSE
specex-0.7.13.dist-info/METADATA
specex-0.7.13.dist-info/WHEEL
specex-0.7.13.dist-info/entry_points.txt
specex-0.7.13.dist-info/top_level.txt
specex-0.7.13.dist-info/RECORD
