Metadata-Version: 2.4
Name: specex
Version: 0.7.13
Summary: Extract spectra from fits cubes
Author: Maurizio D'Addona
Author-email: mauritiusdadd@gmail.com
Maintainer: Maurizio D'Addona
Maintainer-email: mauritiusdadd@gmail.com
License: BSD 3-Clause License
Project-URL: documentation, https://python-specex.readthedocs.io/en/latest
Project-URL: repository, https://github.com/mauritiusdadd/python-specex
Keywords: spectroscopy,spectra,spectrum,spectral cubes
Classifier: Development Status :: 3 - Alpha
Classifier: Intended Audience :: Science/Research
Classifier: Topic :: Multimedia :: Graphics :: Graphics Conversion
Classifier: Programming Language :: Python :: 3
Requires-Python: >=3.7
License-File: LICENSE
Requires-Dist: numpy
Requires-Dist: scipy
Requires-Dist: astropy
Requires-Dist: matplotlib
Provides-Extra: animations
Requires-Dist: imageio; extra == "animations"
Provides-Extra: regions
Requires-Dist: regions; extra == "regions"
Provides-Extra: advanced
Requires-Dist: reproject; extra == "advanced"
Provides-Extra: redrock
Requires-Dist: numba; extra == "redrock"
Requires-Dist: sqlalchemy; extra == "redrock"
Requires-Dist: healpy; extra == "redrock"
Requires-Dist: requests; extra == "redrock"
Requires-Dist: fitsio; extra == "redrock"
Requires-Dist: photutils; extra == "redrock"
Requires-Dist: h5py; extra == "redrock"
Provides-Extra: all
Requires-Dist: specex[advanced,animations,redrock,regions]; extra == "all"
Provides-Extra: test
Requires-Dist: coverage; extra == "test"
Dynamic: license-file
